<?xml version = '1.0' encoding = 'UTF-8'?>
<TableSpaceOraclev10g class="oracle.dbtools.crest.model.design.storage.oracle.v10g.TableSpaceOraclev10g" name="UIM_DI01" directorySegmentName="seg_0" id="7391018C-3A51-9A5A-0EE4-E2EE35E5699F">
<sourceConnName>uim_di01</sourceConnName>
<sourceObjSchema>UIM_DI01</sourceObjSchema>
<sourceObjName>UIM_DI01</sourceObjName>
<createdBy>pd</createdBy>
<createdTime>2015-08-25 12:15:50 UTC</createdTime>
<generatorID>Benutzergeneriert</generatorID>
<ownerDesignName>udm2020-di</ownerDesignName>
<emUniformSize>0</emUniformSize>
<extentManagement>LOCAL</extentManagement>
</TableSpaceOraclev10g>