<?xml version = '1.0' encoding = 'UTF-8'?>
<Relation class="oracle.dbtools.crest.model.design.logical.Relation" name="SYS_C003624494" directorySegmentName="seg_0" id="E358A9E3-51CD-305D-CD75-C991E2E019B5">
<createdBy>pd</createdBy>
<createdTime>2015-08-25 12:22:53 UTC</createdTime>
<generatorID>235FAF62-EE72-1C79-E0FE-E0FA31C3D165</generatorID>
<ownerDesignName>udm2020-di</ownerDesignName>
<engineerTo>
<item key="E63EBEC0-0CD8-5457-5AC4-FD4300DBE9CA" value="true"/>
</engineerTo>
<sourcePk>7BE5BEDF-CCFA-CBEC-B888-8702D45C79FC</sourcePk>
<identifying>true</identifying>
<optionalSource>true</optionalSource>
<optionalTarget>false</optionalTarget>
<sourceCardinality>1</sourceCardinality>
<sourceEntity>7A2812FD-CB49-E652-7816-B1122FE221C8</sourceEntity>
<targetCardinalityString>*</targetCardinalityString>
<targetEntity>012FE6C7-27DD-CEEA-F285-0B491BFC3AD2</targetEntity>
<transferable>true</transferable>
<deleteRule>NO ACTION</deleteRule>
</Relation>